peerai_python_sdk/__init__.py
peerai_python_sdk/get_upload_url.py
peerai_python_sdk/upload_google_cloud.py
peerai_python_sdk/uploadlib.py
peerai_python_sdk-0.1.2.dist-info/WHEEL
peerai_python_sdk-0.1.2.dist-info/METADATA
peerai_python_sdk-0.1.2.dist-info/RECORD
