Metadata-Version: 2.1
Name: peerai-python-sdk
Version: 0.1.2
Summary: 
Author: Surat Teerapittayanon
Author-email: surat@peer-ai.com
Requires-Python: >=3.9,<4.0
Classifier: Programming Language :: Python :: 3
Classifier: Programming Language :: Python :: 3.10
Classifier: Programming Language :: Python :: 3.9
Requires-Dist: ipfs-cid (>=1.0.0,<2.0.0)
Requires-Dist: numpy (>=1.24.3,<2.0.0)
Requires-Dist: onnx (>=1.14.0,<2.0.0)
Requires-Dist: onnx-tool (>=0.6.4,<0.7.0)
Requires-Dist: requests (>=2.30.0,<3.0.0)
Requires-Dist: requests-toolbelt (>=1.0.0,<2.0.0)
Requires-Dist: tqdm (>=4.65.0,<5.0.0)
